src/__init__.py
src/__main__.py
src/api_client.py
src/git_utils.py
src/mcp_tools.py
ai_code_recorder_client-1.0.3.dist-info/METADATA
ai_code_recorder_client-1.0.3.dist-info/WHEEL
ai_code_recorder_client-1.0.3.dist-info/entry_points.txt
ai_code_recorder_client-1.0.3.dist-info/licenses/LICENSE
ai_code_recorder_client-1.0.3.dist-info/RECORD
