Metadata-Version: 2.4
Name: ai-code-recorder-client
Version: 1.0.3
Summary: AI代码记录器 MCP 客户端 - 通过 MCP 协议记录 AI 生成的代码片段
Project-URL: Homepage, https://github.com/ai-code-team/ai-code-recorder
Project-URL: Repository, https://github.com/ai-code-team/ai-code-recorder
Project-URL: Issues, https://github.com/ai-code-team/ai-code-recorder/issues
Project-URL: Documentation, https://github.com/ai-code-team/ai-code-recorder/blob/main/README.md
Author-email: AI Code Recorder Team <contact@aicodeteam.com>
Maintainer-email: AI Code Recorder Team <contact@aicodeteam.com>
License: MIT
License-File: LICENSE
Keywords: ai,code,cursor,development,mcp,recorder
Classifier: Development Status :: 4 - Beta
Classifier: Intended Audience :: Developers
Classifier: License :: OSI Approved :: MIT License
Classifier: Operating System :: OS Independent
Classifier: Programming Language :: Python :: 3
Classifier: Programming Language :: Python :: 3.8
Classifier: Programming Language :: Python :: 3.9
Classifier: Programming Language :: Python :: 3.10
Classifier: Programming Language :: Python :: 3.11
Classifier: Programming Language :: Python :: 3.12
Classifier: Topic :: Software Development :: Code Generators
Classifier: Topic :: Software Development :: Libraries :: Python Modules
Requires-Python: >=3.8
Requires-Dist: fastmcp>=0.1.0
Requires-Dist: requests>=2.31.0
